{
   "type": "categories-carousel",
   "content": {
      "items": [{
            "title": "Миски",
            "url": "/bowls/pos_tipmick__miska/",
            "image": {
               "desktop": "/media/x/img2/miks1.png"
            }
         },
         {
            "title": "Набори мисок",
            "url": "/bowls/pos_tipmick__nabor-misok/",
            "image": {
               "desktop": "/media/x/img2/miks2.png"
            }
         },
         {
            "title": "Нержавіюча сталь",
            "url": "/bowls/mis_mater_mic__nerzhavejuschaja-stal/",
            "image": {
               "desktop": "/media/x/img2/miks4.png"
            }
         },
         {
            "title": "Пластикові",
            "url": "/bowls/mis_mater_mic__plastik/",
            "image": {
               "desktop": "/media/x/img2/miks5.png"
            }
         },
         {
            "title": "Скляні",
            "url": "/bowls/mis_mater_mic__steklo/",
            "image": {
               "desktop": "/media/x/img2/miks6.png"
            }
         },
         {
            "title": "З кришкою",
            "url": "/bowls/ocoben_miski__s-kryshkoj/",
            "image": {
               "desktop": "/media/x/img2/miks7.png"
            }
         },
         {
            "title": "З друшляком",
            "url": "/bowls/ocoben_miski__s-durshlagom/",
            "image": {
               "desktop": "/media/x/img2/miks8.png"
            }
         }
      ]
   }
}