{
   "type": "categories-carousel",
   "content": {
      "items": [{
            "title": "Організатори для столових приборів",
            "url": "/for-kitchen-utensils/tip_kuh_aks__organajzer-dlja-stolovyh-priborov/",
            "image": {
               "desktop": "/media/x/img2/prinadleghnosti1.png"
            }
         },
         {
            "title": "Підставки для кухонного приладдя",
            "url": "/for-kitchen-utensils/tip_kuh_aks__podstavka-dlja-kuhonnyh-prinadlezhnostej/",
            "image": {
               "desktop": "/media/x/img2/prinadleghnosti2.png"
            }
         },
         {
            "title": "Підставки для гарячого",
            "url": "/for-kitchen-utensils/tip_kuh_aks__podstavka-dlja-gorjachego/",
            "image": {
               "desktop": "/media/x/img2/prinadleghnosti3.png"
            }
         }
      ]
   }
}